LICENSE
MANIFEST.in
README.md
setup.py
pythonnest/__init__.py
pythonnest/admin.py
pythonnest/colors.py
pythonnest/context_processors.py
pythonnest/defaults.py
pythonnest/iniconf.py
pythonnest/models.py
pythonnest/root_urls.py
pythonnest/rpc_api.py
pythonnest/views.py
pythonnest/xmlrpc.py
pythonnest.egg-info/PKG-INFO
pythonnest.egg-info/SOURCES.txt
pythonnest.egg-info/dependency_links.txt
pythonnest.egg-info/entry_points.txt
pythonnest.egg-info/not-zip-safe
pythonnest.egg-info/requires.txt
pythonnest.egg-info/top_level.txt
pythonnest/__pycache__/__init__.cpython-36.pyc
pythonnest/__pycache__/admin.cpython-36.pyc
pythonnest/__pycache__/defaults.cpython-36.pyc
pythonnest/__pycache__/iniconf.cpython-36.pyc
pythonnest/__pycache__/models.cpython-36.pyc
pythonnest/__pycache__/root_urls.cpython-36.pyc
pythonnest/__pycache__/views.cpython-36.pyc
pythonnest/__pycache__/xmlrpc.cpython-36.pyc
pythonnest/locale/fr_FR/LC_MESSAGES/django.mo
pythonnest/locale/fr_FR/LC_MESSAGES/django.po
pythonnest/management/__init__.py
pythonnest/management/__pycache__/__init__.cpython-36.pyc
pythonnest/management/commands/__init__.py
pythonnest/management/commands/export.py
pythonnest/management/commands/import.py
pythonnest/management/commands/update.py
pythonnest/migrations/0001_initial.py
pythonnest/migrations/0002_auto_20141005_2218.py
pythonnest/migrations/0003_auto_20160105_2338.py
pythonnest/migrations/0004_auto_20160117_1805.py
pythonnest/migrations/0005_auto_20180421_1000.py
pythonnest/migrations/__init__.py
pythonnest/migrations/__pycache__/0001_initial.cpython-36.pyc
pythonnest/migrations/__pycache__/0002_auto_20141005_2218.cpython-36.pyc
pythonnest/migrations/__pycache__/0003_auto_20160105_2338.cpython-36.pyc
pythonnest/migrations/__pycache__/0004_auto_20160117_1805.cpython-36.pyc
pythonnest/migrations/__pycache__/0005_auto_20180421_1000.cpython-36.pyc
pythonnest/migrations/__pycache__/__init__.cpython-36.pyc
pythonnest/static/README
pythonnest/static/favicon.png
pythonnest/static/images/ajax-loader.gif
pythonnest/static/pythonnest/dev/doc/source/_static/favicon.png
pythonnest/static/pythonnest/dev/doc/source/_static/logo.png
pythonnest/static/scripts/jquery-1.8.2.js
pythonnest/static/scripts/scripts.js
